extendedjson/__init__.py
extendedjson-0.1.3.dist-info/LICENSE
extendedjson-0.1.3.dist-info/WHEEL
extendedjson-0.1.3.dist-info/METADATA
extendedjson-0.1.3.dist-info/RECORD
